final/controller.sv
module controller(
    input logic         clk,
    input logic  [31:0] instruction,
    output logic        write_mem,
    output logic [2:0]  funct3,
    output logic [31:0] write_address,
    output logic [31:0] write_data,
    output logic [31:0] read_address
);
    // RISC-V instruction fields
    logic [6:0] opcode;
    logic [4:0] rd, rs1, rs2;
    logic [2:0] funct3_instr;
    logic [6:0] funct7;
    logic [31:0] imm_u;
    
    // Register file
    logic [31:0] registers [0:31];
    
    // Program counter
    logic [31:0] pc = 32'd0;
    
    // Instruction decode
    assign opcode = instruction[6:0];
    assign rd = instruction[11:7];
    assign funct3_instr = instruction[14:12];
    assign rs1 = instruction[19:15];
    assign rs2 = instruction[24:20];
    assign funct7 = instruction[31:25];
    assign imm_u = {instruction[31:12], 12'b0}; // U-type immediate
    
    // Initialize registers to 0
    initial begin
        for (int i = 0; i < 32; i++) begin
            registers[i] = 32'd0;
        end
    end
    
    // Memory access outputs
    assign write_mem = 1'b0; // We're not writing to memory in this implementation
    assign funct3 = 3'b010;  // Word access
    assign write_address = 32'd0;
    assign write_data = 32'd0;
    assign read_address = pc;  // Read from program counter address
    
    // Execute instruction
    always_ff @(posedge clk) begin
        case (opcode)
            7'b0110111: begin // LUI
                if (rd != 0) registers[rd] <= imm_u;
                pc <= pc + 4;
            end
            
            7'b0110011: begin // R-type instructions
                if (funct7 == 7'b0000001 && funct3_instr == 3'b001) begin // MULH
                    if (rd != 0) begin
                        // Sign-extended multiplication, take upper 32 bits
                        logic signed [63:0] product;
                        logic signed [31:0] a, b;
                        logic signed [31:0] result;
                        a = registers[rs1];
                        b = registers[rs2];
                        product = a * b;
                        result = product[63:32];
                        registers[rd] <= product[63:32];
                    end
                end
                pc <= pc + 4;
            end
            
            default: begin
                pc <= pc + 4; // Skip unknown instructions
            end
        endcase
    end
    
endmodule

final/memory.sv
// RV32I memory module
//
// Implements 8kB of actual memory in the address range of 0x00000000 to
// 0x00001FFF, which can be written to or read from in words (4 bytes), 
// half words (2 bytes), or single bytes. Word accesses are aligned to four-byte 
// boundaries, and half-word access are aligned to two-byte boundaries.
// Half-word and sigle-byte reads are either sign extended or zero extended to 
// 32 bits, depending on the msb of funct3. The value of funct3 should be 3'b010 
// when fetching instructions as it is during execution of lw / sw instructions. 
// Addresses outside of the physical address space are read as 32'd0. The memory 
// can be initialized by specifying via the INIT_FILE parameter the name of a 
// text file containing 2,048 lines of 32-bit hex values. If no file name is 
// specified, the memory is initialized to all 0s.
//
// The memory module also implements some memory-mapped peripherals: 8-bit PWM 
// generators for each of the user LED (0xFFFFFFFF, R/W), RED (0xFFFFFFFE, R/W), 
// GREEN (0xFFFFFFFD, R/W), and BLUE (0xFFFFFFFC, R/W), a running timer that 
// counts the number of milliseconds (mod 2^32) since the processor 
// started (0xFFFFFFF8, R), and a running timer that counts the number of 
// microseconds (mod 2^32) since the processor started (0xFFFFFFF4, R).

module memory #(
    parameter INIT_FILE = ""
)(
    input logic     clk, 
    input logic     write_mem, 
    input logic     [2:0] funct3,   // funct3 should be 3'b010 when fetching instructions as it is during execution of lw / sw instructions
    input logic     [31:0] write_address, 
    input logic     [31:0] write_data, 
    input logic     [31:0] read_address, 
    output logic    [31:0] read_data, 
    output logic    led,            // Active-high PWM output for user LED
    output logic    red,            // Active-high PWM output for red LED
    output logic    green,          // Active-high PWM output for green LED
    output logic    blue            // Active-high PWM output for blue LED
);

    logic [31:0] read_value = 32'd0;

    // Declare variables associated with memory-mapped peripherals
    logic [31:0] leds = 32'd0;      // Address 0xFFFFFFFC, R/W, four 8-bit PWM duty-cycle values for the user LED and the RGB LEDs
    logic [31:0] millis = 32'd0;    // Address 0xFFFFFFF8, R, count of milliseconds since processor started (mod 2^32)
    logic [31:0] micros = 32'd0;    // Address 0xFFFFFFF4, R, count of microseconds since processor started (mod 2^32)

    logic [7:0] pwm_counter = 8'd0;
    logic [13:0] millis_counter = 14'd0;
    logic [3:0] micros_counter = 4'd0;

    // Declare memory array for 8kB of actual memory
    logic [31:0] memory [0:2047];

    // Declare variables to save the two LSBs of the read address and funct3
    logic read_address0;
    logic read_address1;
    logic read_word;
    logic read_half;
    logic read_unsigned;

    // Declare variables to make iverilog stop yelling at us
    logic [15:0] read_value10;
    logic [15:0] read_value32;
    logic [7:0] read_value0;
    logic [7:0] read_value1;
    logic [7:0] read_value2;
    logic [7:0] read_value3;
    logic sign_bit0;
    logic sign_bit1;
    logic sign_bit2;
    logic sign_bit3;

    int i;

    // Initialize memory array
    initial begin
        if (INIT_FILE) begin
            $readmemb(INIT_FILE, memory);
        end
        else begin
            for (i = 0; i < 2048; i++) begin
                memory[i] = 32'd0;
            end
        end
    end

    // Handle memory reads
    always_ff @(posedge clk) begin
        read_address1 <= read_address[1];
        read_address0 <= read_address[0];
        read_word <= funct3[1];
        read_half <= funct3[0];
        read_unsigned <= funct3[2];

        if (read_address[31:13] == 19'd0) begin
            read_value <= memory[read_address[12:2]];
        end
        else if (read_address[31:13] == 19'h7FFFF) begin
            case(read_address[12:2])
                11'h7FF:
                    read_value <= leds;
                11'h7FE:
                    read_value <= millis;
                11'h7FD:
                    read_value <= micros;
                default:
                    read_value <= 32'd0;
            endcase
        end
        else begin
            read_value <= 32'd0;
        end
    end

    assign read_value10 = read_value[15:0];
    assign read_value32 = read_value[31:16];
    assign read_value0 = read_value[7:0];
    assign read_value1 = read_value[15:8];
    assign read_value2 = read_value[23:16];
    assign read_value3 = read_value[31:24];
    assign sign_bit0 = read_value[7];
    assign sign_bit1 = read_value[15];
    assign sign_bit2 = read_value[23];
    assign sign_bit3 = read_value[31];

    always_comb begin
        if (read_word) begin
            read_data = read_value;
        end
        else if (read_half && !read_unsigned) begin
            read_data = read_address1 ? {{16{sign_bit3}}, read_value32} : {{16{sign_bit1}}, read_value10};
        end
        else if (read_half && read_unsigned) begin
            read_data = read_address1 ? {16'd0, read_value32} : {16'd0, read_value10};
        end
        else if (!read_half && !read_unsigned) begin
            case ({read_address1, read_address0})
                2'b00:
                    read_data = {{24{sign_bit0}}, read_value0};
                2'b01:
                    read_data = {{24{sign_bit1}}, read_value1};
                2'b10:
                    read_data = {{24{sign_bit2}}, read_value2};
                2'b11:
                    read_data = {{24{sign_bit3}}, read_value3};
            endcase
        end
        else if (!read_half && read_unsigned) begin
            case ({read_address1, read_address0})
                2'b00:
                    read_data = {24'd0, read_value0};
                2'b01:
                    read_data = {24'd0, read_value1};
                2'b10:
                    read_data = {24'd0, read_value2};
                2'b11:
                    read_data = {24'd0, read_value3};
            endcase
        end
        else begin
            read_data = read_value;
        end
    end

    // Handle memory writes
    always_ff @(posedge clk) begin
        if (write_mem) begin
            if (write_address[31:13] == 19'd0) begin
                if (funct3[1]) begin
                    memory[write_address[12:2]] <= write_data;
                end
                else if (funct3[0]) begin
                    if (write_address[1])
                        memory[write_address[12:2]][31:16] <= write_data[15:0];
                    else
                        memory[write_address[12:2]][15:0] <= write_data[15:0];
                end
                else begin
                    case (write_address[1:0])
                        2'b00:
                            memory[write_address[12:2]][7:0] <= write_data[7:0];
                        2'b01:
                            memory[write_address[12:2]][15:8] <= write_data[7:0];
                        2'b10:
                            memory[write_address[12:2]][23:16] <= write_data[7:0];
                        2'b11:
                            memory[write_address[12:2]][31:24] <= write_data[7:0];
                    endcase
                end
            end
            else if (write_address[31:2] == 30'h3FFFFFFF) begin
                if (funct3[1]) begin
                    leds <= write_data;
                end
                else if (funct3[0]) begin
                    if (write_address[1])
                        leds[31:16] <= write_data[15:0];
                    else
                        leds[15:0] <= write_data[15:0];
                end
                else begin
                    case (write_address[1:0])
                        2'b00:
                            leds[7:0] <= write_data[7:0];
                        2'b01:
                            leds[15:8] <= write_data[7:0];
                        2'b10:
                            leds[23:16] <= write_data[7:0];
                        2'b11:
                            leds[31:24] <= write_data[7:0];
                    endcase
                end
            end
        end
    end

    // Implement PWM control for LED / RGB outputs
    always_ff @(posedge clk) begin
        pwm_counter <= pwm_counter + 1;
    end

    assign led = (pwm_counter < leds[31:24]);
    assign red = (pwm_counter < leds[23:16]);
    assign green = (pwm_counter < leds[15:8]);
    assign blue = (pwm_counter < leds[7:0]);

    // Implement millis counter
    always_ff @(posedge clk) begin
        if (millis_counter == 11999) begin
            millis_counter <= 14'd0;
            millis <= millis + 1;
        end
        else begin
            millis_counter <= millis_counter + 1;
        end
    end

    // Implement micros counter
    always_ff @(posedge clk) begin
        if (micros_counter == 11) begin
            micros_counter <= 4'd0;
            micros <= micros + 1;
        end
        else begin
            micros_counter <= micros_counter + 1;
        end
    end

endmodule

final/top.sv
`include "controller.sv"
`include "memory.sv"

module top(
    input logic clk
);
    // Signals between controller and memory
    logic write_mem;
    logic [2:0] funct3;
    logic [31:0] write_address;
    logic [31:0] write_data;
    logic [31:0] read_address;
    logic [31:0] read_data;
    logic led, red, green, blue;
    
    // Instantiate memory module
    memory #(
        .INIT_FILE("test.txt")
    ) mem (
        .clk(clk),
        .write_mem(write_mem),
        .funct3(funct3),
        .write_address(write_address),
        .write_data(write_data),
        .read_address(read_address),
        .read_data(read_data),
        .led(led),
        .red(red),
        .green(green),
        .blue(blue)
    );
    
    // Instantiate controller
    controller ctrl (
        .clk(clk),
        .instruction(read_data),
        .write_mem(write_mem),
        .funct3(funct3),
        .write_address(write_address),
        .write_data(write_data),
        .read_address(read_address)
    );
    
endmodule

final/tb.sv
`timescale 10ns/10ns
`include "top.sv"

module top_tb;
    logic clk = 0;
    
    top u0(.clk(clk));
    
    // Test values for registers
    initial begin
        $dumpfile("top.vcd");
        $dumpvars(0, top_tb);
        
        // Monitor register values for validation
        $monitor("Time=%0t, PC=%0d, Reg[8]=%h, Reg[9]=%h, Reg[10]=%h", 
                 $time, u0.ctrl.pc, u0.ctrl.registers[8], u0.ctrl.registers[9], 
                 u0.ctrl.registers[10]);
        
        #2000
        $finish;
    end
    
    // Generate clock
    always begin
        #4 clk = ~clk;
    end
    
endmodule

final/top.vcd
$date
	Sun May  4 16:49:14 2025
$end
$version
	Icarus Verilog
$end
$timescale
	10ns
$end
$scope module top_tb $end
$var reg 1 ! clk $end
$scope module u0 $end
$var wire 1 ! clk $end
$var wire 3 " funct3 [2:0] $end
$var wire 32 # write_address [31:0] $end
$var wire 32 $ write_data [31:0] $end
$var wire 1 % write_mem $end
$var wire 1 & red $end
$var wire 32 ' read_data [31:0] $end
$var wire 32 ( read_address [31:0] $end
$var wire 1 ) led $end
$var wire 1 * green $end
$var wire 1 + blue $end
$scope module ctrl $end
$var wire 1 ! clk $end
$var wire 3 , funct3 [2:0] $end
$var wire 32 - read_address [31:0] $end
$var wire 32 . write_address [31:0] $end
$var wire 32 / write_data [31:0] $end
$var wire 1 % write_mem $end
$var wire 5 0 rs2 [4:0] $end
$var wire 5 1 rs1 [4:0] $end
$var wire 5 2 rd [4:0] $end
$var wire 7 3 opcode [6:0] $end
$var wire 32 4 instruction [31:0] $end
$var wire 32 5 imm_u [31:0] $end
$var wire 7 6 funct7 [6:0] $end
$var wire 3 7 funct3_instr [2:0] $end
$var reg 32 8 pc [31:0] $end
$scope begin $ivl_for_loop0 $end
$var integer 32 9 i [31:0] $end
$upscope $end
$scope begin $unm_blk_7 $end
$var reg 32 : a [31:0] $end
$var reg 32 ; b [31:0] $end
$var reg 64 < product [63:0] $end
$var reg 32 = result [31:0] $end
$upscope $end
$upscope $end
$scope module mem $end
$var wire 1 ! clk $end
$var wire 3 > funct3 [2:0] $end
$var wire 32 ? read_address [31:0] $end
$var wire 32 @ write_address [31:0] $end
$var wire 32 A write_data [31:0] $end
$var wire 1 % write_mem $end
$var wire 1 B sign_bit3 $end
$var wire 1 C sign_bit2 $end
$var wire 1 D sign_bit1 $end
$var wire 1 E sign_bit0 $end
$var wire 1 & red $end
$var wire 16 F read_value32 [15:0] $end
$var wire 8 G read_value3 [7:0] $end
$var wire 8 H read_value2 [7:0] $end
$var wire 16 I read_value10 [15:0] $end
$var wire 8 J read_value1 [7:0] $end
$var wire 8 K read_value0 [7:0] $end
$var wire 1 ) led $end
$var wire 1 * green $end
$var wire 1 + blue $end
$var reg 32 L leds [31:0] $end
$var reg 32 M micros [31:0] $end
$var reg 4 N micros_counter [3:0] $end
$var reg 32 O millis [31:0] $end
$var reg 14 P millis_counter [13:0] $end
$var reg 8 Q pwm_counter [7:0] $end
$var reg 1 R read_address0 $end
$var reg 1 S read_address1 $end
$var reg 32 T read_data [31:0] $end
$var reg 1 U read_half $end
$var reg 1 V read_unsigned $end
$var reg 32 W read_value [31:0] $end
$var reg 1 X read_word $end
$upscope $end
$upscope $end
$upscope $end
$enddefinitions $end
#0
$dumpvars
xX
b0 W
xV
xU
b0 T
xS
xR
b0 Q
b0 P
b0 O
b0 N
b0 M
b0 L
b0 K
b0 J
b0 I
b0 H
b0 G
b0 F
0E
0D
0C
0B
b0 A
b0 @
b0 ?
b10 >
bx =
bx <
bx ;
bx :
b100000 9
b0 8
b0 7
b0 6
b0 5
b0 4
b0 3
b0 2
b0 1
b0 0
b0 /
b0 .
b0 -
b10 ,
0+
0*
0)
b0 (
b0 '
0&
0%
b0 $
b0 #
b10 "
0!
$end
#4
b1111111111111111000000000000000 5
b111111 6
b11111 0
b11111 1
b1 2
b110111 3
b1000000010110111 I
b111111111111111 F
b10110111 K
b10000000 J
b11111111 H
b1111111 G
1E
1D
1C
b1111111111111111000000010110111 '
b1111111111111111000000010110111 4
b1111111111111111000000010110111 T
b1111111111111111000000010110111 W
0V
0U
1X
0R
0S
b1 Q
b1 P
b1 N
b100 (
b100 -
b100 ?
b100 8
1!
#8
0!
#12
b0 5
b0 6
b0 0
b0 1
b0 2
b10011 3
b10011 '
b10011 4
b10011 T
b10011 I
b0 F
b10011 K
b0 J
b0 H
b0 G
0E
0D
0C
b1000 (
b1000 -
b1000 ?
b1000 8
b10 N
b10 P
b10 Q
b10011 W
1!
#16
0!
#20
b11111010000011010001000000000000 5
b1111101 6
b11010 1
b1 7
b10 2
b110111 3
b11111010000011010001000100110111 '
b11111010000011010001000100110111 4
b11111010000011010001000100110111 T
b1000100110111 I
b1111101000001101 F
b110111 K
b10001 J
b1101 H
b11111010 G
1B
b11111010000011010001000100110111 W
b11 Q
b11 P
b11 N
b1100 (
b1100 -
b1100 ?
b1100 8
1!
#24
0!
#28
b0 5
b0 6
b0 1
b0 7
b0 2
b10011 3
b10011 '
b10011 4
b10011 T
b10011 I
b0 F
b10011 K
b0 J
b0 H
b0 G
0B
b10000 (
b10000 -
b10000 ?
b10000 8
b100 N
b100 P
b100 Q
b10011 W
1!
#32
0!
#36
b10001000001001000000000000 5
b1 6
b10 0
b1 1
b1 7
b11 2
b110011 3
b10001000001001000110110011 '
b10001000001001000110110011 4
b10001000001001000110110011 T
b1001000110110011 I
b1000100000 F
b10110011 K
b10010001 J
b100000 H
b10 G
1E
1D
b10001000001001000110110011 W
b101 Q
b101 P
b101 N
b10100 (
b10100 -
b10100 ?
b10100 8
1!
#40
0!
#44
bx000000000000 5
bx 6
bx 0
bx 1
bx 7
bx 2
bx 3
bx '
bx 4
bx T
bx I
bx F
bx K
bx J
bx H
bx G
xE
xD
xC
xB
b11000 (
b11000 -
b11000 ?
b11000 8
b110 N
b110 P
b110 Q
bx W
b11111101000001101000101011111001 =
b1111110100000110100010101111100101111000000000000000000000000000 <
b11111010000011010001000000000000 ;
b1111111111111111000000000000000 :
1!
#48
0!
#52
b111 Q
b111 P
b111 N
b11100 (
b11100 -
b11100 ?
b11100 8
1!
#56
0!
#60
b100000 (
b100000 -
b100000 ?
b100000 8
b1000 N
b1000 P
b1000 Q
1!
#64
0!
#68
b1001 Q
b1001 P
b1001 N
b100100 (
b100100 -
b100100 ?
b100100 8
1!
#72
0!
#76
b101000 (
b101000 -
b101000 ?
b101000 8
b1010 N
b1010 P
b1010 Q
1!
#80
0!
#84
b1011 Q
b1011 P
b1011 N
b101100 (
b101100 -
b101100 ?
b101100 8
1!
#88
0!
#92
b110000 (
b110000 -
b110000 ?
b110000 8
b1 M
b0 N
b1100 P
b1100 Q
1!
#96
0!
#100
b1101 Q
b1101 P
b1 N
b110100 (
b110100 -
b110100 ?
b110100 8
1!
#104
0!
#108
b111000 (
b111000 -
b111000 ?
b111000 8
b10 N
b1110 P
b1110 Q
1!
#112
0!
#116
b1111 Q
b1111 P
b11 N
b111100 (
b111100 -
b111100 ?
b111100 8
1!
#120
0!
#124
b1000000 (
b1000000 -
b1000000 ?
b1000000 8
b100 N
b10000 P
b10000 Q
1!
#128
0!
#132
b10001 Q
b10001 P
b101 N
b1000100 (
b1000100 -
b1000100 ?
b1000100 8
1!
#136
0!
#140
b1001000 (
b1001000 -
b1001000 ?
b1001000 8
b110 N
b10010 P
b10010 Q
1!
#144
0!
#148
b10011 Q
b10011 P
b111 N
b1001100 (
b1001100 -
b1001100 ?
b1001100 8
1!
#152
0!
#156
b1010000 (
b1010000 -
b1010000 ?
b1010000 8
b1000 N
b10100 P
b10100 Q
1!
#160
0!
#164
b10101 Q
b10101 P
b1001 N
b1010100 (
b1010100 -
b1010100 ?
b1010100 8
1!
#168
0!
#172
b1011000 (
b1011000 -
b1011000 ?
b1011000 8
b1010 N
b10110 P
b10110 Q
1!
#176
0!
#180
b10111 Q
b10111 P
b1011 N
b1011100 (
b1011100 -
b1011100 ?
b1011100 8
1!
#184
0!
#188
b1100000 (
b1100000 -
b1100000 ?
b1100000 8
b10 M
b0 N
b11000 P
b11000 Q
1!
#192
0!
#196
b11001 Q
b11001 P
b1 N
b1100100 (
b1100100 -
b1100100 ?
b1100100 8
1!
#200
0!
#204
b1101000 (
b1101000 -
b1101000 ?
b1101000 8
b10 N
b11010 P
b11010 Q
1!
#208
0!
#212
b11011 Q
b11011 P
b11 N
b1101100 (
b1101100 -
b1101100 ?
b1101100 8
1!
#216
0!
#220
b1110000 (
b1110000 -
b1110000 ?
b1110000 8
b100 N
b11100 P
b11100 Q
1!
#224
0!
#228
b11101 Q
b11101 P
b101 N
b1110100 (
b1110100 -
b1110100 ?
b1110100 8
1!
#232
0!
#236
b1111000 (
b1111000 -
b1111000 ?
b1111000 8
b110 N
b11110 P
b11110 Q
1!
#240
0!
#244
b11111 Q
b11111 P
b111 N
b1111100 (
b1111100 -
b1111100 ?
b1111100 8
1!
#248
0!
#252
b10000000 (
b10000000 -
b10000000 ?
b10000000 8
b1000 N
b100000 P
b100000 Q
1!
#256
0!
#260
b100001 Q
b100001 P
b1001 N
b10000100 (
b10000100 -
b10000100 ?
b10000100 8
1!
#264
0!
#268
b10001000 (
b10001000 -
b10001000 ?
b10001000 8
b1010 N
b100010 P
b100010 Q
1!
#272
0!
#276
b100011 Q
b100011 P
b1011 N
b10001100 (
b10001100 -
b10001100 ?
b10001100 8
1!
#280
0!
#284
b10010000 (
b10010000 -
b10010000 ?
b10010000 8
b11 M
b0 N
b100100 P
b100100 Q
1!
#288
0!
#292
b100101 Q
b100101 P
b1 N
b10010100 (
b10010100 -
b10010100 ?
b10010100 8
1!
#296
0!
#300
b10011000 (
b10011000 -
b10011000 ?
b10011000 8
b10 N
b100110 P
b100110 Q
1!
#304
0!
#308
b100111 Q
b100111 P
b11 N
b10011100 (
b10011100 -
b10011100 ?
b10011100 8
1!
#312
0!
#316
b10100000 (
b10100000 -
b10100000 ?
b10100000 8
b100 N
b101000 P
b101000 Q
1!
#320
0!
#324
b101001 Q
b101001 P
b101 N
b10100100 (
b10100100 -
b10100100 ?
b10100100 8
1!
#328
0!
#332
b10101000 (
b10101000 -
b10101000 ?
b10101000 8
b110 N
b101010 P
b101010 Q
1!
#336
0!
#340
b101011 Q
b101011 P
b111 N
b10101100 (
b10101100 -
b10101100 ?
b10101100 8
1!
#344
0!
#348
b10110000 (
b10110000 -
b10110000 ?
b10110000 8
b1000 N
b101100 P
b101100 Q
1!
#352
0!
#356
b101101 Q
b101101 P
b1001 N
b10110100 (
b10110100 -
b10110100 ?
b10110100 8
1!
#360
0!
#364
b10111000 (
b10111000 -
b10111000 ?
b10111000 8
b1010 N
b101110 P
b101110 Q
1!
#368
0!
#372
b101111 Q
b101111 P
b1011 N
b10111100 (
b10111100 -
b10111100 ?
b10111100 8
1!
#376
0!
#380
b11000000 (
b11000000 -
b11000000 ?
b11000000 8
b100 M
b0 N
b110000 P
b110000 Q
1!
#384
0!
#388
b110001 Q
b110001 P
b1 N
b11000100 (
b11000100 -
b11000100 ?
b11000100 8
1!
#392
0!
#396
b11001000 (
b11001000 -
b11001000 ?
b11001000 8
b10 N
b110010 P
b110010 Q
1!
#400
0!
#404
b110011 Q
b110011 P
b11 N
b11001100 (
b11001100 -
b11001100 ?
b11001100 8
1!
#408
0!
#412
b11010000 (
b11010000 -
b11010000 ?
b11010000 8
b100 N
b110100 P
b110100 Q
1!
#416
0!
#420
b110101 Q
b110101 P
b101 N
b11010100 (
b11010100 -
b11010100 ?
b11010100 8
1!
#424
0!
#428
b11011000 (
b11011000 -
b11011000 ?
b11011000 8
b110 N
b110110 P
b110110 Q
1!
#432
0!
#436
b110111 Q
b110111 P
b111 N
b11011100 (
b11011100 -
b11011100 ?
b11011100 8
1!
#440
0!
#444
b11100000 (
b11100000 -
b11100000 ?
b11100000 8
b1000 N
b111000 P
b111000 Q
1!
#448
0!
#452
b111001 Q
b111001 P
b1001 N
b11100100 (
b11100100 -
b11100100 ?
b11100100 8
1!
#456
0!
#460
b11101000 (
b11101000 -
b11101000 ?
b11101000 8
b1010 N
b111010 P
b111010 Q
1!
#464
0!
#468
b111011 Q
b111011 P
b1011 N
b11101100 (
b11101100 -
b11101100 ?
b11101100 8
1!
#472
0!
#476
b11110000 (
b11110000 -
b11110000 ?
b11110000 8
b101 M
b0 N
b111100 P
b111100 Q
1!
#480
0!
#484
b111101 Q
b111101 P
b1 N
b11110100 (
b11110100 -
b11110100 ?
b11110100 8
1!
#488
0!
#492
b11111000 (
b11111000 -
b11111000 ?
b11111000 8
b10 N
b111110 P
b111110 Q
1!
#496
0!
#500
b111111 Q
b111111 P
b11 N
b11111100 (
b11111100 -
b11111100 ?
b11111100 8
1!
#504
0!
#508
b100000000 (
b100000000 -
b100000000 ?
b100000000 8
b100 N
b1000000 P
b1000000 Q
1!
#512
0!
#516
b1000001 Q
b1000001 P
b101 N
b100000100 (
b100000100 -
b100000100 ?
b100000100 8
1!
#520
0!
#524
b100001000 (
b100001000 -
b100001000 ?
b100001000 8
b110 N
b1000010 P
b1000010 Q
1!
#528
0!
#532
b1000011 Q
b1000011 P
b111 N
b100001100 (
b100001100 -
b100001100 ?
b100001100 8
1!
#536
0!
#540
b100010000 (
b100010000 -
b100010000 ?
b100010000 8
b1000 N
b1000100 P
b1000100 Q
1!
#544
0!
#548
b1000101 Q
b1000101 P
b1001 N
b100010100 (
b100010100 -
b100010100 ?
b100010100 8
1!
#552
0!
#556
b100011000 (
b100011000 -
b100011000 ?
b100011000 8
b1010 N
b1000110 P
b1000110 Q
1!
#560
0!
#564
b1000111 Q
b1000111 P
b1011 N
b100011100 (
b100011100 -
b100011100 ?
b100011100 8
1!
#568
0!
#572
b100100000 (
b100100000 -
b100100000 ?
b100100000 8
b110 M
b0 N
b1001000 P
b1001000 Q
1!
#576
0!
#580
b1001001 Q
b1001001 P
b1 N
b100100100 (
b100100100 -
b100100100 ?
b100100100 8
1!
#584
0!
#588
b100101000 (
b100101000 -
b100101000 ?
b100101000 8
b10 N
b1001010 P
b1001010 Q
1!
#592
0!
#596
b1001011 Q
b1001011 P
b11 N
b100101100 (
b100101100 -
b100101100 ?
b100101100 8
1!
#600
0!
#604
b100110000 (
b100110000 -
b100110000 ?
b100110000 8
b100 N
b1001100 P
b1001100 Q
1!
#608
0!
#612
b1001101 Q
b1001101 P
b101 N
b100110100 (
b100110100 -
b100110100 ?
b100110100 8
1!
#616
0!
#620
b100111000 (
b100111000 -
b100111000 ?
b100111000 8
b110 N
b1001110 P
b1001110 Q
1!
#624
0!
#628
b1001111 Q
b1001111 P
b111 N
b100111100 (
b100111100 -
b100111100 ?
b100111100 8
1!
#632
0!
#636
b101000000 (
b101000000 -
b101000000 ?
b101000000 8
b1000 N
b1010000 P
b1010000 Q
1!
#640
0!
#644
b1010001 Q
b1010001 P
b1001 N
b101000100 (
b101000100 -
b101000100 ?
b101000100 8
1!
#648
0!
#652
b101001000 (
b101001000 -
b101001000 ?
b101001000 8
b1010 N
b1010010 P
b1010010 Q
1!
#656
0!
#660
b1010011 Q
b1010011 P
b1011 N
b101001100 (
b101001100 -
b101001100 ?
b101001100 8
1!
#664
0!
#668
b101010000 (
b101010000 -
b101010000 ?
b101010000 8
b111 M
b0 N
b1010100 P
b1010100 Q
1!
#672
0!
#676
b1010101 Q
b1010101 P
b1 N
b101010100 (
b101010100 -
b101010100 ?
b101010100 8
1!
#680
0!
#684
b101011000 (
b101011000 -
b101011000 ?
b101011000 8
b10 N
b1010110 P
b1010110 Q
1!
#688
0!
#692
b1010111 Q
b1010111 P
b11 N
b101011100 (
b101011100 -
b101011100 ?
b101011100 8
1!
#696
0!
#700
b101100000 (
b101100000 -
b101100000 ?
b101100000 8
b100 N
b1011000 P
b1011000 Q
1!
#704
0!
#708
b1011001 Q
b1011001 P
b101 N
b101100100 (
b101100100 -
b101100100 ?
b101100100 8
1!
#712
0!
#716
b101101000 (
b101101000 -
b101101000 ?
b101101000 8
b110 N
b1011010 P
b1011010 Q
1!
#720
0!
#724
b1011011 Q
b1011011 P
b111 N
b101101100 (
b101101100 -
b101101100 ?
b101101100 8
1!
#728
0!
#732
b101110000 (
b101110000 -
b101110000 ?
b101110000 8
b1000 N
b1011100 P
b1011100 Q
1!
#736
0!
#740
b1011101 Q
b1011101 P
b1001 N
b101110100 (
b101110100 -
b101110100 ?
b101110100 8
1!
#744
0!
#748
b101111000 (
b101111000 -
b101111000 ?
b101111000 8
b1010 N
b1011110 P
b1011110 Q
1!
#752
0!
#756
b1011111 Q
b1011111 P
b1011 N
b101111100 (
b101111100 -
b101111100 ?
b101111100 8
1!
#760
0!
#764
b110000000 (
b110000000 -
b110000000 ?
b110000000 8
b1000 M
b0 N
b1100000 P
b1100000 Q
1!
#768
0!
#772
b1100001 Q
b1100001 P
b1 N
b110000100 (
b110000100 -
b110000100 ?
b110000100 8
1!
#776
0!
#780
b110001000 (
b110001000 -
b110001000 ?
b110001000 8
b10 N
b1100010 P
b1100010 Q
1!
#784
0!
#788
b1100011 Q
b1100011 P
b11 N
b110001100 (
b110001100 -
b110001100 ?
b110001100 8
1!
#792
0!
#796
b110010000 (
b110010000 -
b110010000 ?
b110010000 8
b100 N
b1100100 P
b1100100 Q
1!
#800
0!
#804
b1100101 Q
b1100101 P
b101 N
b110010100 (
b110010100 -
b110010100 ?
b110010100 8
1!
#808
0!
#812
b110011000 (
b110011000 -
b110011000 ?
b110011000 8
b110 N
b1100110 P
b1100110 Q
1!
#816
0!
#820
b1100111 Q
b1100111 P
b111 N
b110011100 (
b110011100 -
b110011100 ?
b110011100 8
1!
#824
0!
#828
b110100000 (
b110100000 -
b110100000 ?
b110100000 8
b1000 N
b1101000 P
b1101000 Q
1!
#832
0!
#836
b1101001 Q
b1101001 P
b1001 N
b110100100 (
b110100100 -
b110100100 ?
b110100100 8
1!
#840
0!
#844
b110101000 (
b110101000 -
b110101000 ?
b110101000 8
b1010 N
b1101010 P
b1101010 Q
1!
#848
0!
#852
b1101011 Q
b1101011 P
b1011 N
b110101100 (
b110101100 -
b110101100 ?
b110101100 8
1!
#856
0!
#860
b110110000 (
b110110000 -
b110110000 ?
b110110000 8
b1001 M
b0 N
b1101100 P
b1101100 Q
1!
#864
0!
#868
b1101101 Q
b1101101 P
b1 N
b110110100 (
b110110100 -
b110110100 ?
b110110100 8
1!
#872
0!
#876
b110111000 (
b110111000 -
b110111000 ?
b110111000 8
b10 N
b1101110 P
b1101110 Q
1!
#880
0!
#884
b1101111 Q
b1101111 P
b11 N
b110111100 (
b110111100 -
b110111100 ?
b110111100 8
1!
#888
0!
#892
b111000000 (
b111000000 -
b111000000 ?
b111000000 8
b100 N
b1110000 P
b1110000 Q
1!
#896
0!
#900
b1110001 Q
b1110001 P
b101 N
b111000100 (
b111000100 -
b111000100 ?
b111000100 8
1!
#904
0!
#908
b111001000 (
b111001000 -
b111001000 ?
b111001000 8
b110 N
b1110010 P
b1110010 Q
1!
#912
0!
#916
b1110011 Q
b1110011 P
b111 N
b111001100 (
b111001100 -
b111001100 ?
b111001100 8
1!
#920
0!
#924
b111010000 (
b111010000 -
b111010000 ?
b111010000 8
b1000 N
b1110100 P
b1110100 Q
1!
#928
0!
#932
b1110101 Q
b1110101 P
b1001 N
b111010100 (
b111010100 -
b111010100 ?
b111010100 8
1!
#936
0!
#940
b111011000 (
b111011000 -
b111011000 ?
b111011000 8
b1010 N
b1110110 P
b1110110 Q
1!
#944
0!
#948
b1110111 Q
b1110111 P
b1011 N
b111011100 (
b111011100 -
b111011100 ?
b111011100 8
1!
#952
0!
#956
b111100000 (
b111100000 -
b111100000 ?
b111100000 8
b1010 M
b0 N
b1111000 P
b1111000 Q
1!
#960
0!
#964
b1111001 Q
b1111001 P
b1 N
b111100100 (
b111100100 -
b111100100 ?
b111100100 8
1!
#968
0!
#972
b111101000 (
b111101000 -
b111101000 ?
b111101000 8
b10 N
b1111010 P
b1111010 Q
1!
#976
0!
#980
b1111011 Q
b1111011 P
b11 N
b111101100 (
b111101100 -
b111101100 ?
b111101100 8
1!
#984
0!
#988
b111110000 (
b111110000 -
b111110000 ?
b111110000 8
b100 N
b1111100 P
b1111100 Q
1!
#992
0!
#996
b1111101 Q
b1111101 P
b101 N
b111110100 (
b111110100 -
b111110100 ?
b111110100 8
1!
#1000
0!
#1004
b111111000 (
b111111000 -
b111111000 ?
b111111000 8
b110 N
b1111110 P
b1111110 Q
1!
